ravenmcp_demo/__init__.py
ravenmcp_demo-0.1.0.dist-info/WHEEL
ravenmcp_demo-0.1.0.dist-info/entry_points.txt
ravenmcp_demo-0.1.0.dist-info/METADATA
ravenmcp_demo-0.1.0.dist-info/RECORD
