Metadata-Version: 2.3
Name: ravenmcp-demo
Version: 0.1.0
Summary: Add your description here
Author-email: 979919125@qq.com
Requires-Dist: mcp[cli]>=1.25.0
Requires-Python: >=3.13
